MANIFEST.in
README.rst
setup.py
src/hachibee_sphinx_theme/__init__.py
src/hachibee_sphinx_theme/__init__.pyc
src/hachibee_sphinx_theme.egg-info/PKG-INFO
src/hachibee_sphinx_theme.egg-info/SOURCES.txt
src/hachibee_sphinx_theme.egg-info/dependency_links.txt
src/hachibee_sphinx_theme.egg-info/top_level.txt
src/hachibee_sphinx_theme/hachibee/layout.html
src/hachibee_sphinx_theme/hachibee/localtoc.html
src/hachibee_sphinx_theme/hachibee/page.html
src/hachibee_sphinx_theme/hachibee/relations.html
src/hachibee_sphinx_theme/hachibee/searchbox.html
src/hachibee_sphinx_theme/hachibee/sourcelink.html
src/hachibee_sphinx_theme/hachibee/theme.conf
src/hachibee_sphinx_theme/hachibee/coffee/menuselection.coffee
src/hachibee_sphinx_theme/hachibee/coffee/phantom_header.coffee
src/hachibee_sphinx_theme/hachibee/static/backtop.js
src/hachibee_sphinx_theme/hachibee/static/genericons-regular-webfont.eot
src/hachibee_sphinx_theme/hachibee/static/genericons-regular-webfont.svg
src/hachibee_sphinx_theme/hachibee/static/genericons-regular-webfont.ttf
src/hachibee_sphinx_theme/hachibee/static/genericons-regular-webfont.woff
src/hachibee_sphinx_theme/hachibee/static/genericons.css
src/hachibee_sphinx_theme/hachibee/static/main.css
src/hachibee_sphinx_theme/hachibee/static/main.js
src/hachibee_sphinx_theme/hachibee/static/mobile.css
src/hachibee_sphinx_theme/hachibee/stylus/colors.styl
src/hachibee_sphinx_theme/hachibee/stylus/directives.styl
src/hachibee_sphinx_theme/hachibee/stylus/genericons.styl
src/hachibee_sphinx_theme/hachibee/stylus/main.styl
src/hachibee_sphinx_theme/hachibee/stylus/mobile.styl
src/hachibee_sphinx_theme/hachibee/stylus/normalize.styl
src/hachibee_sphinx_theme/hachibee/stylus/reset.styl
src/hachibee_sphinx_theme/hachibee/stylus/roles.styl
src/hachibee_sphinx_theme/hachibee/stylus/variables.styl
src/hachibee_sphinx_theme/hachibee/stylus/widget-decorations.styl