Metadata-Version: 1.1
Name: hachibee-sphinx-theme
Version: 0.2.5
Summary: a simple sphinx theme
Home-page: https://github.com/hachibeeDI/Sphinx-hachibee-theme
Author: OGURA_Daiki
Author-email: 8hachibee125@gmail.com
License: MIT
Keywords: sphinx,sphinx.theme
Platform: UNKNOWN
Classifier: Development Status :: 4 - Beta
Classifier: Environment :: Web Environment
Classifier: License :: OSI Approved :: MIT License
Classifier: Programming Language :: Python
Classifier: Topic :: Software Development :: Documentation
